{
	"data_columns": ["Close"],
	"model": {
		"loss": "mse",
		"optimizer": "adam",
		"layers": [
			{
				"type": "lstm",
				"neurons": 200,
				"return_seq": true,
				"dropout_rate": 0,
                "input_timesteps": 60,
                "input_dim": 1
            },
			{
				"type": "dropout",
				"dropout_rate": 0
			},
			{
				"type": "lstm",
				"neurons": 200,
				"return_seq": true,
				"dropout_rate": 0
            },
			{
				"type": "dropout",
				"dropout_rate": 0
			},
			{
				"type": "lstm",
				"neurons": 100,
				"return_seq": false,
				"dropout_rate": 0
            },
			{
				"type": "dropout",
				"dropout_rate": 0
			},
			{
				"type": "dense",
				"neurons": 1,
				"activation": "linear"
			}
		]
	}
}
